capidup/__init__.py
capidup/finddups.py
capidup/py3compat.py
capidup/version.py
capidup-1.1.0.dist-info/DESCRIPTION.rst
capidup-1.1.0.dist-info/METADATA
capidup-1.1.0.dist-info/RECORD
capidup-1.1.0.dist-info/WHEEL
capidup-1.1.0.dist-info/metadata.json
capidup-1.1.0.dist-info/top_level.txt
